CONTRIBUTING.md
LICENSE
MANIFEST.in
README.md
setup.py
freon/__init__.py
freon/cache.py
freon.egg-info/PKG-INFO
freon.egg-info/SOURCES.txt
freon.egg-info/dependency_links.txt
freon.egg-info/not-zip-safe
freon.egg-info/requires.txt
freon.egg-info/top_level.txt
freon/backends/__init__.py
freon/backends/base.py
freon/backends/memory.py
freon/backends/redis.py
freon/serializers/__init__.py
freon/serializers/base.py
freon/serializers/json.py
freon/serializers/msgpack.py
freon/serializers/pickle.py
tests/__init__.py
tests/test_cache.py
tests/test_serializers.py
tests/backends/__init__.py
tests/backends/test_memory.py
tests/backends/test_redis.py